Workbook

Sheet 1_Assumptions
A1: Browser-Fleet Economics — Assumptions
A2: Gelb hinterlegt = Input. Blau geschrieben. Aendere eine Zahl, alles Folgende rechnet sich neu.
A4: INFRASTRUKTUR
A5: VPS-Kosten srv1622293 (EUR/Monat) | B5: 60 | C5: Hostinger KVM-Linie. Bei Plan-Wechsel anpassen.
A6: vCPU srv1622293 | B6: 4 | C6: Aktuelle Allokation. PM2 + Playwright + Ollama teilen sich.
A7: RAM (GB) | B7: 8
A8: Reserviert fuer Ollama (vCPU) | B8: 1 | C8: qwen3:4b laeuft auf 1 vCPU.
A9: Verfuegbare vCPU fuer Scanner | B9: =B4-B6 | C9: auto
A10: Parallele Worker pro vCPU | B10: 2 | C10: Playwright headless mit ~500 MB pro Instanz.
A11: Max parallele Scanner | B11: =B7*B8 | C11: auto
A12: SCAN-PROFILE
A13: Median Scan-Dauer (Sekunden) | B13: 45 | C13: Inkl. Page-Load, Network-Inventar, Consent-Check.
A14: Overhead-Faktor (Retries, Idle, Warm-Up) | B14: 1.5 | C14: 1.5 = 50% Aufschlag. 1.0 = keine Reserve.
A15: Effektive Sekunden pro Scan | B15: =B11*B12 | C15: auto
A16: Sekunden pro Monat (30 Tage) | B16: =30*24*3600 | C16: auto
A17: Max Scans/Monat auf srv1622293 | B17: =B9*B14/B13 | C17: auto: parallel_capacity * seconds/month / seconds_per_scan
A18: STRIPE & ZAHLUNG
A19: Stripe-Gebuehr (Prozent) | B19: 0.014 | C19: 1.4% EU-Karten.
A20: Stripe-Gebuehr (Fixum, EUR) | B20: 0.25
A21: MIX-ANNAHME
A22: Free-Audit-Anteil | B22: 0.6 | C22: One-time scan. Konvertiert ~5% zu Starter.
A23: Starter-Anteil | B23: 0.25 | C23: 1 Domain, monatlicher Re-Scan.
A24: Growth-Anteil | B24: 0.1 | C24: 3 Domains, taegliches Monitoring.
A25: Agency-Anteil | B25: 0.04 | C25: 10 Kundenseiten, White-Label.
A26: Enterprise-Anteil | B26: 0.01 | C26: Unlimited (Fair-Use Cap unten).
A27: Mix-Summe (muss = 100% sein) | B27: =SUM(B20:B24) | C27: auto
A28: ENTERPRISE FAIR-USE
A29: Fair-Use Domain-Cap Enterprise | B29: 30 | C29: Cap fuer Scans-Modellierung. Vertraglich >, im Pricing 'unlimited'.

Sheet 2_Tier_Economics
A1: Pro Tier: Preis, Scan-Volumen, variable Kosten, Marge
A3: Tier | B3: Preis (EUR) | C3: Domains | D3: Scans / Monat | E3: Var. Kosten | F3: Stripe-Gebuehr | G3: Deckungsbeitrag | H3: Marge % | I3: Modell-Notiz
A4: Free Audit | B4: 0 | C4: 1 | D4: 1 | E4: =D4*('1_Assumptions'!$B$5/'1_Assumptions'!$B$15) | F4: =IF(B4=0,0,B4*'1_Assumptions'!$B$17+'1_Assumptions'!$B$18) | G4: =B4-E4-F4 | H4: =IF(B4=0,0,G4/B4) | I4: One-time. Wird nur 1x pro Lead gerechnet.
A5: Starter | B5: 49 | C5: 1 | D5: 1 | E5: =D5*('1_Assumptions'!$B$5/'1_Assumptions'!$B$15) | F5: =IF(B5=0,0,B5*'1_Assumptions'!$B$17+'1_Assumptions'!$B$18) | G5: =B5-E5-F5 | H5: =IF(B5=0,0,G5/B5) | I5: Monatlicher Re-Scan, 1 Domain.
A6: Growth | B6: 179 | C6: 3 | D6: 90 | E6: =D6*('1_Assumptions'!$B$5/'1_Assumptions'!$B$15) | F6: =IF(B6=0,0,B6*'1_Assumptions'!$B$17+'1_Assumptions'!$B$18) | G6: =B6-E6-F6 | H6: =IF(B6=0,0,G6/B6) | I6: 3 Domains * 30 Tage Monitoring = 90 Scans.
A7: Agency | B7: 499 | C7: 10 | D7: 300 | E7: =D7*('1_Assumptions'!$B$5/'1_Assumptions'!$B$15) | F7: =IF(B7=0,0,B7*'1_Assumptions'!$B$17+'1_Assumptions'!$B$18) | G7: =B7-E7-F7 | H7: =IF(B7=0,0,G7/B7) | I7: 10 Kundenseiten * 30 Tage = 300 Scans.
A8: Enterprise | B8: 998 | C8: ='1_Assumptions'!$B$27 | D8: =C8*30 | E8: =D8*('1_Assumptions'!$B$5/'1_Assumptions'!$B$15) | F8: =IF(B8=0,0,B8*'1_Assumptions'!$B$17+'1_Assumptions'!$B$18) | G8: =B8-E8-F8 | H8: =IF(B8=0,0,G8/B8) | I8: Fair-Use Cap aus Assumptions. Preis-Floor 998 (pricing.ts).
A10: Cost-per-scan-Formel: (VPS-Kosten / Max-Scans-pro-Monat) — siehe Sheet 1, Zellen B5 und B15.

Sheet 3_Capacity_BreakEven
A1: Capacity & Break-Even auf srv1622293
A2: Gewichtetes Scan-Profil aus Mix-Annahme (Sheet 1) gegen Infrastrukturkapazitaet.
A4: MIX (aus Sheet 1)
A5: Free-Anteil | B5: ='1_Assumptions'!$B$20
A6: Starter-Anteil | B6: ='1_Assumptions'!$B$21
A7: Growth-Anteil | B7: ='1_Assumptions'!$B$22
A8: Agency-Anteil | B8: ='1_Assumptions'!$B$23
A9: Enterprise-Anteil | B9: ='1_Assumptions'!$B$24
A10: Summe (muss 100% sein) | B10: =SUM(B5:B9) | C10: 100% = sauber kalibriert.
A11: GEWICHTETER SCAN-BEDARF
A12: Avg Scans / Tenant / Monat | B12: =B5*'2_Tier_Economics'!D4 + B6*'2_Tier_Economics'!D5 + B7*'2_Tier_Economics'!D6 + B8*'2_Tier_Economics'!D7 + B9*'2_Tier_Economics'!D8 | C12: Erwartungswert ueber alle Tiers.
A13: Max Scans / Monat (Infra-Cap) | B13: ='1_Assumptions'!$B$15 | C13: Sheet 1, B15.
A14: Max Tenants auf srv1622293 (theoretisch) | B14: =B12/B11 | C14: Bei aktuellem Mix.
A15: Sicherheitsabschlag (Spike-Reserve) | B15: 0.7 | C15: 70% nutzbar lassen 30% Headroom fuer Spikes.
A16: Max Tenants empfohlen | B16: =B13*B14 | C16: auto
A17: BREAK-EVEN
A18: Fixkosten / Monat (VPS + Domains + Supabase) | B18: 200 | C18: Aus ADR-001: < 200 EUR/Mo total.
A19: Avg Deckungsbeitrag / Tenant | B19: =B5*'2_Tier_Economics'!G4 + B6*'2_Tier_Economics'!G5 + B7*'2_Tier_Economics'!G6 + B8*'2_Tier_Economics'!G7 + B9*'2_Tier_Economics'!G8 | C19: Gewichteter Deckungsbeitrag aus Sheet 2 Spalte G.
A20: Break-Even Tenant-Anzahl | B20: =B17/B18 | C20: =Fixkosten / Avg-DB.
A21: HEADROOM
A22: Headroom bis Migration (Tenants) | B22: =B15-B19 | C22: Wieviele Tenants ueber Break-Even hinaus auf srv1622293 passen.

Sheet 4_Scaling_Roadmap
A1: Scaling Roadmap — 5 Phasen, ADR-001-Trigger
A3: Phase | B3: Tenant-Range | C3: Infrastruktur | D3: Worker-Pool | E3: Mtl. Kosten | F3: Migrations-Trigger
A4: Phase 1 — Bootstrap | B4: 0 – 50 | C4: 1 VPS (srv1622293) | D4: PM2 + systemd, 4–8 parallele Worker | E4: < 200 EUR | F4: —
A5: Phase 2 — Co-Pilot | B5: 50 – 200 | C5: + 2. VPS, Docker Compose | D5: Round-Robin via Traefik | E5: < 500 EUR | F5: Trigger D: > 8 parallele Worker sustained
A6: Phase 3 — NATS-Cutover | B6: 200 – 500 | C6: + NATS JetStream | D6: Bus-getriebene Worker, kein LISTEN/NOTIFY mehr | E6: < 1.500 EUR | F6: Trigger A: > 5M Events/Tag oder p95 LISTEN > 500ms
A7: Phase 4 — Schema-per-Tenant | B7: 500 – 1.000 | C7: Postgres-Schema-Split, ggf. dedizierte DB pro Enterprise | D7: Dedizierte Worker-Pools fuer Enterprise | E7: < 4.000 EUR | F7: Trigger C: > 200 aktive Tenants oder p95-RLS > 300ms
A8: Phase 5 — Multi-Region EU | B8: 1.000+ | C8: Frankfurt + Paris/Stockholm, K8s (managed) oder Hetzner/OVH | D8: K8s-Operator fuer Worker-Lifecycle | E8: > 8.000 EUR | F8: Trigger D: > 4 Worker-VPS UND DevOps-Headcount
A10: Trigger-Details: docs/adr/ADR-001-event-backbone.md §4.

Sheet 5_Recommendations
A1: Operative Empfehlungen aus dem Modell
A3: # | B3: Empfehlung | C3: Begruendung & Aktion
A4: 1 | B4: Free-Tier hart limitieren | C4: Free-Audit ist Lead-Generator. Bei > 60% Mix-Anteil wird er zum Kostenfresser. Aktion: kein Account, kein Re-Scan, harte Rate-Limits pro IP/Domain.
A5: 2 | B5: Starter-Marge taeglich validieren | C5: EUR 49 mit 1 Domain + monatlichem Re-Scan ist nach dem Rebalance vom 18.05. enges Sweet-Spot. Stripe + Cost-per-Scan duerfen nicht > 25% des Tier-Preises kommen. Sheet 2 Zelle H5 wachhalten.
A6: 3 | B6: Growth ist das Profit-Center | C6: EUR 179 mit 3 Domains taeglich ist das Tier mit hoechster absoluter Marge. Sales-Fokus: Starter -> Growth-Upgrade nach 30 Tagen.
A7: 4 | B7: Agency-Quota an White-Label binden | C7: EUR 499 fuer 10 Kundenseiten. Wenn ein Agency-Kunde via API > 10 Domains pushed, automatische Quota-Warnung. Overage-Pricing oder Upgrade-Flow.
A8: 5 | B8: Enterprise: 'unlimited' braucht Fair-Use | C8: Vertraglich 'unlimitierte Domains' (pricing.ts). Praktisch begrenzt durch srv1622293-Kapazitaet. Fair-Use-Cap in Assumptions Sheet 1 B27 (Default 30 Domains) — bei Ueberschreitung Eskalation an Sales.
A9: 6 | B9: Zweiter Worker-VPS vor Tenant 30 | C9: Headroom (Sheet 3 B21) wird bei aktuellem Mix bereits ab ~20-30 Tenants knapp. Phase 2 starten BEVOR sustained-overload eintritt.
A10: 7 | B10: Drift-Cron jitteren | C10: Bei taeglichem Monitoring fuer Growth + Agency: gestaffelte Slots ueber 24h, nicht alle um 00:00. Sonst Spike fuer 30-60 Min, Rest des Tages idle. Ohne Jitter: kuenstlich erzeugter Burst-Bedarf.
A11: 8 | B11: Stripe-SEPA fuer DE-Kunden anbieten | C11: Bei EUR 49 / 179 sind 1.4% + 0.25 EUR Karten-Fee schmerzhaft (besonders fuer Starter). SEPA Direct Debit: 0.8% + 0.25 EUR. Margen-Effekt auf Starter sichtbar in Sheet 2.
